weas_widget/__init__.py
weas_widget/atoms_viewer.py
weas_widget/base_class.py
weas_widget/base_widget.py
weas_widget/camera.py
weas_widget/config.py
weas_widget/data.py
weas_widget/fermi_surface.py
weas_widget/phonon.py
weas_widget/server.py
weas_widget/utils.py
weas_widget/weas.py
weas_widget/agent/__init__.py
weas_widget/agent/constants.py
weas_widget/agent/editing_tools.py
weas_widget/agent/operations_tools.py
weas_widget/agent/selection_tools.py
weas_widget/agent/structure_tools.py
weas_widget/agent/style_tools.py
weas_widget/agent/tool_helpers.py
weas_widget/agent/toolkit.py
weas_widget/agent/tools.py
weas_widget/agent/visualization_tools.py
weas_widget/cli/__init__.py
weas_widget/cli/template.html
weas_widget/cli/template.js
weas_widget/operators/__init__.py
weas_widget/operators/atoms.py
weas_widget/operators/mesh.py
weas_widget/operators/object.py
weas_widget/operators/ops.py
weas_widget/operators/selection.py
weas_widget/operators/transform.py
weas_widget/plugins/__init__.py
weas_widget/plugins/any_mesh.py
weas_widget/plugins/bond.py
weas_widget/plugins/cell.py
weas_widget/plugins/highlight.py
weas_widget/plugins/instanced_mesh_pritimive.py
weas_widget/plugins/isosurface.py
weas_widget/plugins/lattice_plane.py
weas_widget/plugins/species.py
weas_widget/plugins/text.py
weas_widget/plugins/vector_field.py
weas_widget/plugins/volume_slice.py
weas_widget/static/widget.css
weas_widget/static/widget.js
weas_widget-0.2.4.dist-info/METADATA
weas_widget-0.2.4.dist-info/WHEEL
weas_widget-0.2.4.dist-info/entry_points.txt
weas_widget-0.2.4.dist-info/licenses/LICENSE
weas_widget-0.2.4.dist-info/RECORD
