Metadata-Version: 2.4
Name: weas_widget
Version: 0.2.4
Summary: A widget to visualize and interact with atomistic structures in Jupyter Notebook.
Project-URL: Documentation, https://weas-widget.readthedocs.io
Project-URL: Source, https://github.com/superstar54/weas-widget
Author-email: Xing Wang <xingwang1991@gmail.com>
License: MIT License
License-File: LICENSE
Keywords: atomistic,edit,visualize
Classifier: Development Status :: 1 - Planning
Classifier: License :: OSI Approved :: MIT License
Classifier: Operating System :: MacOS :: MacOS X
Classifier: Operating System :: POSIX :: Linux
Classifier: Programming Language :: Python
Classifier: Programming Language :: Python :: 3.6
Classifier: Programming Language :: Python :: 3.7
Classifier: Programming Language :: Python :: 3.8
Classifier: Programming Language :: Python :: 3.9
Classifier: Programming Language :: Python :: 3.10
Classifier: Programming Language :: Python :: 3.11
Classifier: Programming Language :: Python :: 3.12
Classifier: Topic :: Scientific/Engineering
Requires-Python: >=3.6
Requires-Dist: anywidget>=0.9.11
Requires-Dist: appdirs>=1.4.4
Requires-Dist: ase
Requires-Dist: click>=8.1.7
Requires-Dist: numpy
Requires-Dist: requests
Requires-Dist: scikit-image
Requires-Dist: seekpath
Provides-Extra: aiida
Requires-Dist: aiida-core; extra == 'aiida'
Provides-Extra: dev
Requires-Dist: jupyterlab; extra == 'dev'
Requires-Dist: watchfiles; extra == 'dev'
Provides-Extra: docs
Requires-Dist: ipykernel; extra == 'docs'
Requires-Dist: nbsphinx; extra == 'docs'
Requires-Dist: sphinx-rtd-theme; extra == 'docs'
Requires-Dist: sphinx~=7.2; extra == 'docs'
Provides-Extra: langchain
Requires-Dist: langchain-widget[openai]; extra == 'langchain'
Provides-Extra: pre-commit
Requires-Dist: pre-commit~=2.2; extra == 'pre-commit'
Requires-Dist: pylint~=2.17.4; extra == 'pre-commit'
Provides-Extra: tests
Requires-Dist: httpx; extra == 'tests'
Requires-Dist: playwright; extra == 'tests'
Requires-Dist: pytest-cov<2.11,~=2.7; extra == 'tests'
Requires-Dist: pytest~=7.0; extra == 'tests'
